LICENSE.md
README.md
pyfa_converter/__init__.py
pyfa_converter/depends.py
pyfa_converter/main.py
pyfa_converter/utils/__init__.py
pyfa_converter/utils/deprecation.py
pyfa_converter/utils/deprecation_message.py
pyfa_converter-1.0.5.0.dist-info/LICENSE.md
pyfa_converter-1.0.5.0.dist-info/METADATA
pyfa_converter-1.0.5.0.dist-info/WHEEL
pyfa_converter-1.0.5.0.dist-info/RECORD
